kirami_cli-0.1.1.dist-info/METADATA
kirami_cli-0.1.1.dist-info/WHEEL
kirami_cli-0.1.1.dist-info/entry_points.txt
kirami_cli-0.1.1.dist-info/licenses/LICENSE
kirami_cli/__init__.py
kirami_cli/__main__.py
kirami_cli/cli/__init__.py
kirami_cli/cli/commands/__init__.py
kirami_cli/cli/commands/adapter.py
kirami_cli/cli/commands/driver.py
kirami_cli/cli/commands/migrate.py
kirami_cli/cli/commands/plugin.py
kirami_cli/cli/commands/project.py
kirami_cli/cli/commands/self.py
kirami_cli/cli/customize.py
kirami_cli/cli/utils.py
kirami_cli/config/__init__.py
kirami_cli/config/model.py
kirami_cli/config/parser.py
kirami_cli/consts.py
kirami_cli/exceptions.py
kirami_cli/extensions.py
kirami_cli/handlers/__init__.py
kirami_cli/handlers/adapter.py
kirami_cli/handlers/data.py
kirami_cli/handlers/driver.py
kirami_cli/handlers/meta.py
kirami_cli/handlers/pip.py
kirami_cli/handlers/plugin.py
kirami_cli/handlers/process.py
kirami_cli/handlers/project.py
kirami_cli/handlers/reloader.py
kirami_cli/handlers/script.py
kirami_cli/handlers/signal.py
kirami_cli/handlers/store.py
kirami_cli/handlers/venv.py
kirami_cli/i18n.py
kirami_cli/locale/zh_CN/LC_MESSAGES/kirami-cli.mo
kirami_cli/locale/zh_CN/LC_MESSAGES/kirami-cli.po
kirami_cli/log/__init__.py
kirami_cli/py.typed
kirami_cli/template/adapter/cookiecutter.json
kirami_cli/template/adapter/{{cookiecutter.adapter_slug}}/__init__.py
kirami_cli/template/adapter/{{cookiecutter.adapter_slug}}/adapter.py
kirami_cli/template/adapter/{{cookiecutter.adapter_slug}}/bot.py
kirami_cli/template/adapter/{{cookiecutter.adapter_slug}}/config.py
kirami_cli/template/adapter/{{cookiecutter.adapter_slug}}/event.py
kirami_cli/template/adapter/{{cookiecutter.adapter_slug}}/message.py
kirami_cli/template/plugin/cookiecutter.json
kirami_cli/template/plugin/hooks/post_gen_project.py
kirami_cli/template/plugin/{{cookiecutter.plugin_slug}}/__init__.py
kirami_cli/template/plugin/{{cookiecutter.plugin_slug}}/config.py
kirami_cli/template/plugin/{{cookiecutter.plugin_slug}}/plugins/.gitkeep
kirami_cli/template/plugin/{{cookiecutter.plugin_slug}}/service.toml
kirami_cli/template/project/cookiecutter.json
kirami_cli-0.1.1.dist-info/RECORD
