Metadata-Version: 2.1
Name: kirami-cli
Version: 0.1.1
Summary: CLI for KiramiBot
Keywords: kirami bot chatbot onebot
Home-page: https://cli.kiramibot.dev/
Author-Email: Akirami <akiramiaya@outlook.com>
License: MIT
Classifier: Development Status :: 4 - Beta
Classifier: Framework :: Robot Framework
Classifier: Framework :: Robot Framework :: Library
Classifier: License :: OSI Approved :: MIT License
Classifier: Operating System :: OS Independent
Classifier: Programming Language :: Python
Classifier: Programming Language :: Python :: 3
Classifier: Programming Language :: Python :: 3 :: Only
Classifier: Programming Language :: Python :: 3.10
Classifier: Programming Language :: Python :: 3.11
Project-URL: Homepage, https://cli.kiramibot.dev/
Project-URL: Repository, https://github.com/A-kirami/KiramiCLI
Requires-Python: <4.0,>=3.10
Requires-Dist: click>=8.1.7
Requires-Dist: anyio>=4.0.0
Requires-Dist: httpx>=0.25.0
Requires-Dist: jinja2>=3.1.2
Requires-Dist: cashews>=6.2.0
Requires-Dist: wcwidth>=0.2.6
Requires-Dist: tomlkit>=0.12.1
Requires-Dist: pydantic>=2.3.0
Requires-Dist: watchfiles>=0.20.0
Requires-Dist: cookiecutter>=2.3.0
Requires-Dist: virtualenv>=20.24.5
Requires-Dist: typing-extensions>=4.7.1
Requires-Dist: noneprompt>=0.1.9
Requires-Dist: pyfiglet>=1.0.1
Requires-Dist: ruamel-yaml>=0.17.32
